evolution/__init__.py
evolution/utility.py
evolution/algo/__init__.py
evolution/main/AITrainerApp.py
evolution/main/__init__.py
evolution/main/server/PredictorServer.py
evolution/main/server/__init__.py
evolution/main/server/run_prediction.py
evolution/main/server/controllers/ControllerFactory.py
evolution/main/server/controllers/__init__.py
evolution/main/server/controllers/v1/PredictionController.py
evolution/main/server/controllers/v1/__init__.py
evolution/main/server/dto/PredictionResult.py
evolution/main/server/dto/__init__.py
evolution/main/server/services/PredictionService.py
evolution/main/server/services/__init__.py
evolution/plugin/__init__.py
evolution/plugin/inputs/DataCleaner.py
evolution/plugin/inputs/DataExplorer.py
evolution/plugin/inputs/DataTransformer.py
evolution/plugin/inputs/EDA.py
evolution/plugin/inputs/InputDataReader.py
evolution/plugin/inputs/__init__.py
evolution/plugin/inputs/file/FileInputDataReader.py
evolution/plugin/inputs/file/__init__.py
evolution/plugin/model/ModelDataGenerator.py
evolution/plugin/model/TestModelDataGen.py
evolution/plugin/model/__init__.py
evolution/plugin/model/model_registry.py
evolution/plugin/model/evaluators/EvaluatorFactory.py
evolution/plugin/model/evaluators/__init__.py
evolution/plugin/model/evaluators/base.py
evolution/plugin/model/evaluators/classification.py
evolution/plugin/model/evaluators/regression.py
evolution/plugin/model/feature_selectors/FeatureSelectorFactory.py
evolution/plugin/model/feature_selectors/__init__.py
evolution/plugin/model/feature_selectors/base.py
evolution/plugin/model/feature_selectors/permutation.py
evolution/plugin/model/feature_selectors/rfecv.py
evolution/plugin/model/trainers/TrainerFactory.py
evolution/plugin/model/trainers/__init__.py
evolution/plugin/model/trainers/base.py
evolution/plugin/model/trainers/lightgbm.py
evolution/plugin/model/trainers/xgboost.py
evolution/plugin/outputs/IntermidiateOutDataWriter.py
evolution/plugin/outputs/__init__.py
nglm_ai-0.1.4.post14.dist-info/METADATA
nglm_ai-0.1.4.post14.dist-info/WHEEL
nglm_ai-0.1.4.post14.dist-info/top_level.txt
nglm_ai-0.1.4.post14.dist-info/RECORD
