Metadata-Version: 2.4
Name: nglm-ai
Version: 0.1.4.post14
Summary: nglm base build
Author: Ra K
Author-email: your.email@example.com
Requires-Dist: pandas
Requires-Dist: Flask
Requires-Dist: gunicorn
Requires-Dist: pyyaml
Requires-Dist: scikit-learn
Requires-Dist: matplotlib
Requires-Dist: numpy
Requires-Dist: joblib
Requires-Dist: fastapi
Requires-Dist: missingno
Requires-Dist: seaborn
Requires-Dist: lightgbm
Requires-Dist: xgboost
Dynamic: author
Dynamic: author-email
Dynamic: requires-dist
Dynamic: summary
